_mixal
mixal
tests
