Metadata-Version: 2.1
Name: mixal
Version: 1.178.15
Summary: MIX Assembly Language Simulator
Home-page: https://github.com/CyberZHG/MIXAL
Author: CyberZHG
Author-email: CyberZHG@users.noreply.github.com
License: MIT
Platform: UNKNOWN
Classifier: Programming Language :: Python :: 3
Classifier: License :: OSI Approved :: MIT License
Classifier: Operating System :: OS Independent
